[
  {
    "id": "rs-glossary-001",
    "term": "Rust",
    "definition": "Rust说明",
    "category": "Rust",
    "tags": [
      "Rust"
    ],
    "updatedAt": "2026-07-03T00:00:00.000Z"
  },
  {
    "id": "rs-glossary-002",
    "term": "所有权",
    "definition": "所有权说明",
    "category": "Rust",
    "tags": [
      "Rust"
    ],
    "updatedAt": "2026-07-03T00:00:00.000Z"
  },
  {
    "id": "rs-glossary-003",
    "term": "借用",
    "definition": "借用说明",
    "category": "Rust",
    "tags": [
      "Rust"
    ],
    "updatedAt": "2026-07-03T00:00:00.000Z"
  },
  {
    "id": "rs-glossary-004",
    "term": "生命周期",
    "definition": "生命周期说明",
    "category": "Rust",
    "tags": [
      "Rust"
    ],
    "updatedAt": "2026-07-03T00:00:00.000Z"
  },
  {
    "id": "rs-glossary-005",
    "term": "结构体",
    "definition": "结构体说明",
    "category": "Rust",
    "tags": [
      "Rust"
    ],
    "updatedAt": "2026-07-03T00:00:00.000Z"
  },
  {
    "id": "rs-glossary-006",
    "term": "枚举",
    "definition": "枚举说明",
    "category": "Rust",
    "tags": [
      "Rust"
    ],
    "updatedAt": "2026-07-03T00:00:00.000Z"
  },
  {
    "id": "rs-glossary-007",
    "term": "match",
    "definition": "match说明",
    "category": "Rust",
    "tags": [
      "Rust"
    ],
    "updatedAt": "2026-07-03T00:00:00.000Z"
  },
  {
    "id": "rs-glossary-008",
    "term": "Result",
    "definition": "Result说明",
    "category": "Rust",
    "tags": [
      "Rust"
    ],
    "updatedAt": "2026-07-03T00:00:00.000Z"
  },
  {
    "id": "rs-glossary-009",
    "term": "Trait",
    "definition": "Trait说明",
    "category": "Rust",
    "tags": [
      "Rust"
    ],
    "updatedAt": "2026-07-03T00:00:00.000Z"
  },
  {
    "id": "rs-glossary-010",
    "term": "Cargo",
    "definition": "Cargo说明",
    "category": "Rust",
    "tags": [
      "Rust"
    ],
    "updatedAt": "2026-07-03T00:00:00.000Z"
  },
  {
    "id": "rs-glossary-011",
    "term": "闭包",
    "definition": "闭包说明",
    "category": "Rust",
    "tags": [
      "Rust"
    ],
    "updatedAt": "2026-07-03T00:00:00.000Z"
  },
  {
    "id": "rs-glossary-012",
    "term": "迭代器",
    "definition": "迭代器说明",
    "category": "Rust",
    "tags": [
      "Rust"
    ],
    "updatedAt": "2026-07-03T00:00:00.000Z"
  },
  {
    "id": "rs-glossary-013",
    "term": "并发",
    "definition": "并发说明",
    "category": "Rust",
    "tags": [
      "Rust"
    ],
    "updatedAt": "2026-07-03T00:00:00.000Z"
  },
  {
    "id": "rs-glossary-014",
    "term": "异步",
    "definition": "异步说明",
    "category": "Rust",
    "tags": [
      "Rust"
    ],
    "updatedAt": "2026-07-03T00:00:00.000Z"
  },
  {
    "id": "rs-glossary-015",
    "term": "Vec",
    "definition": "Vec说明",
    "category": "Rust",
    "tags": [
      "Rust"
    ],
    "updatedAt": "2026-07-03T00:00:00.000Z"
  },
  {
    "id": "rs-glossary-016",
    "term": "Rust概念15",
    "definition": "Rust概念15说明",
    "category": "Rust",
    "tags": [
      "Rust"
    ],
    "updatedAt": "2026-07-03T00:00:00.000Z"
  },
  {
    "id": "rs-glossary-017",
    "term": "Rust概念16",
    "definition": "Rust概念16说明",
    "category": "Rust",
    "tags": [
      "Rust"
    ],
    "updatedAt": "2026-07-03T00:00:00.000Z"
  },
  {
    "id": "rs-glossary-018",
    "term": "Rust概念17",
    "definition": "Rust概念17说明",
    "category": "Rust",
    "tags": [
      "Rust"
    ],
    "updatedAt": "2026-07-03T00:00:00.000Z"
  },
  {
    "id": "rs-glossary-019",
    "term": "Rust概念18",
    "definition": "Rust概念18说明",
    "category": "Rust",
    "tags": [
      "Rust"
    ],
    "updatedAt": "2026-07-03T00:00:00.000Z"
  },
  {
    "id": "rs-glossary-020",
    "term": "Rust概念19",
    "definition": "Rust概念19说明",
    "category": "Rust",
    "tags": [
      "Rust"
    ],
    "updatedAt": "2026-07-03T00:00:00.000Z"
  },
  {
    "id": "rs-glossary-021",
    "term": "Rust概念20",
    "definition": "Rust概念20说明",
    "category": "Rust",
    "tags": [
      "Rust"
    ],
    "updatedAt": "2026-07-03T00:00:00.000Z"
  },
  {
    "id": "rs-glossary-022",
    "term": "Rust概念21",
    "definition": "Rust概念21说明",
    "category": "Rust",
    "tags": [
      "Rust"
    ],
    "updatedAt": "2026-07-03T00:00:00.000Z"
  },
  {
    "id": "rs-glossary-023",
    "term": "Rust概念22",
    "definition": "Rust概念22说明",
    "category": "Rust",
    "tags": [
      "Rust"
    ],
    "updatedAt": "2026-07-03T00:00:00.000Z"
  },
  {
    "id": "rs-glossary-024",
    "term": "Rust概念23",
    "definition": "Rust概念23说明",
    "category": "Rust",
    "tags": [
      "Rust"
    ],
    "updatedAt": "2026-07-03T00:00:00.000Z"
  },
  {
    "id": "rs-glossary-025",
    "term": "Rust概念24",
    "definition": "Rust概念24说明",
    "category": "Rust",
    "tags": [
      "Rust"
    ],
    "updatedAt": "2026-07-03T00:00:00.000Z"
  },
  {
    "id": "rs-glossary-026",
    "term": "Rust概念25",
    "definition": "Rust概念25说明",
    "category": "Rust",
    "tags": [
      "Rust"
    ],
    "updatedAt": "2026-07-03T00:00:00.000Z"
  },
  {
    "id": "rs-glossary-027",
    "term": "Rust概念26",
    "definition": "Rust概念26说明",
    "category": "Rust",
    "tags": [
      "Rust"
    ],
    "updatedAt": "2026-07-03T00:00:00.000Z"
  },
  {
    "id": "rs-glossary-028",
    "term": "Rust概念27",
    "definition": "Rust概念27说明",
    "category": "Rust",
    "tags": [
      "Rust"
    ],
    "updatedAt": "2026-07-03T00:00:00.000Z"
  },
  {
    "id": "rs-glossary-029",
    "term": "Rust概念28",
    "definition": "Rust概念28说明",
    "category": "Rust",
    "tags": [
      "Rust"
    ],
    "updatedAt": "2026-07-03T00:00:00.000Z"
  },
  {
    "id": "rs-glossary-030",
    "term": "Rust概念29",
    "definition": "Rust概念29说明",
    "category": "Rust",
    "tags": [
      "Rust"
    ],
    "updatedAt": "2026-07-03T00:00:00.000Z"
  },
  {
    "id": "rs-glossary-031",
    "term": "Rust概念30",
    "definition": "Rust概念30说明",
    "category": "Rust",
    "tags": [
      "Rust"
    ],
    "updatedAt": "2026-07-03T00:00:00.000Z"
  },
  {
    "id": "rs-glossary-032",
    "term": "Rust概念31",
    "definition": "Rust概念31说明",
    "category": "Rust",
    "tags": [
      "Rust"
    ],
    "updatedAt": "2026-07-03T00:00:00.000Z"
  },
  {
    "id": "rs-glossary-033",
    "term": "Rust概念32",
    "definition": "Rust概念32说明",
    "category": "Rust",
    "tags": [
      "Rust"
    ],
    "updatedAt": "2026-07-03T00:00:00.000Z"
  },
  {
    "id": "rs-glossary-034",
    "term": "Rust概念33",
    "definition": "Rust概念33说明",
    "category": "Rust",
    "tags": [
      "Rust"
    ],
    "updatedAt": "2026-07-03T00:00:00.000Z"
  },
  {
    "id": "rs-glossary-035",
    "term": "Rust概念34",
    "definition": "Rust概念34说明",
    "category": "Rust",
    "tags": [
      "Rust"
    ],
    "updatedAt": "2026-07-03T00:00:00.000Z"
  },
  {
    "id": "rs-glossary-036",
    "term": "Rust概念35",
    "definition": "Rust概念35说明",
    "category": "Rust",
    "tags": [
      "Rust"
    ],
    "updatedAt": "2026-07-03T00:00:00.000Z"
  },
  {
    "id": "rs-glossary-037",
    "term": "Rust概念36",
    "definition": "Rust概念36说明",
    "category": "Rust",
    "tags": [
      "Rust"
    ],
    "updatedAt": "2026-07-03T00:00:00.000Z"
  },
  {
    "id": "rs-glossary-038",
    "term": "Rust概念37",
    "definition": "Rust概念37说明",
    "category": "Rust",
    "tags": [
      "Rust"
    ],
    "updatedAt": "2026-07-03T00:00:00.000Z"
  },
  {
    "id": "rs-glossary-039",
    "term": "Rust概念38",
    "definition": "Rust概念38说明",
    "category": "Rust",
    "tags": [
      "Rust"
    ],
    "updatedAt": "2026-07-03T00:00:00.000Z"
  },
  {
    "id": "rs-glossary-040",
    "term": "Rust概念39",
    "definition": "Rust概念39说明",
    "category": "Rust",
    "tags": [
      "Rust"
    ],
    "updatedAt": "2026-07-03T00:00:00.000Z"
  },
  {
    "id": "rs-glossary-041",
    "term": "Rust概念40",
    "definition": "Rust概念40说明",
    "category": "Rust",
    "tags": [
      "Rust"
    ],
    "updatedAt": "2026-07-03T00:00:00.000Z"
  },
  {
    "id": "rs-glossary-042",
    "term": "Rust概念41",
    "definition": "Rust概念41说明",
    "category": "Rust",
    "tags": [
      "Rust"
    ],
    "updatedAt": "2026-07-03T00:00:00.000Z"
  },
  {
    "id": "rs-glossary-043",
    "term": "Rust概念42",
    "definition": "Rust概念42说明",
    "category": "Rust",
    "tags": [
      "Rust"
    ],
    "updatedAt": "2026-07-03T00:00:00.000Z"
  },
  {
    "id": "rs-glossary-044",
    "term": "Rust概念43",
    "definition": "Rust概念43说明",
    "category": "Rust",
    "tags": [
      "Rust"
    ],
    "updatedAt": "2026-07-03T00:00:00.000Z"
  },
  {
    "id": "rs-glossary-045",
    "term": "Rust概念44",
    "definition": "Rust概念44说明",
    "category": "Rust",
    "tags": [
      "Rust"
    ],
    "updatedAt": "2026-07-03T00:00:00.000Z"
  },
  {
    "id": "rs-glossary-046",
    "term": "Rust概念45",
    "definition": "Rust概念45说明",
    "category": "Rust",
    "tags": [
      "Rust"
    ],
    "updatedAt": "2026-07-03T00:00:00.000Z"
  },
  {
    "id": "rs-glossary-047",
    "term": "Rust概念46",
    "definition": "Rust概念46说明",
    "category": "Rust",
    "tags": [
      "Rust"
    ],
    "updatedAt": "2026-07-03T00:00:00.000Z"
  },
  {
    "id": "rs-glossary-048",
    "term": "Rust概念47",
    "definition": "Rust概念47说明",
    "category": "Rust",
    "tags": [
      "Rust"
    ],
    "updatedAt": "2026-07-03T00:00:00.000Z"
  },
  {
    "id": "rs-glossary-049",
    "term": "Rust概念48",
    "definition": "Rust概念48说明",
    "category": "Rust",
    "tags": [
      "Rust"
    ],
    "updatedAt": "2026-07-03T00:00:00.000Z"
  },
  {
    "id": "rs-glossary-050",
    "term": "Rust概念49",
    "definition": "Rust概念49说明",
    "category": "Rust",
    "tags": [
      "Rust"
    ],
    "updatedAt": "2026-07-03T00:00:00.000Z"
  },
  {
    "id": "rs-glossary-051",
    "term": "Rust概念50",
    "definition": "Rust概念50说明",
    "category": "Rust",
    "tags": [
      "Rust"
    ],
    "updatedAt": "2026-07-03T00:00:00.000Z"
  },
  {
    "id": "rs-glossary-052",
    "term": "Rust概念51",
    "definition": "Rust概念51说明",
    "category": "Rust",
    "tags": [
      "Rust"
    ],
    "updatedAt": "2026-07-03T00:00:00.000Z"
  },
  {
    "id": "rs-glossary-053",
    "term": "Rust概念52",
    "definition": "Rust概念52说明",
    "category": "Rust",
    "tags": [
      "Rust"
    ],
    "updatedAt": "2026-07-03T00:00:00.000Z"
  },
  {
    "id": "rs-glossary-054",
    "term": "Rust概念53",
    "definition": "Rust概念53说明",
    "category": "Rust",
    "tags": [
      "Rust"
    ],
    "updatedAt": "2026-07-03T00:00:00.000Z"
  },
  {
    "id": "rs-glossary-055",
    "term": "Rust概念54",
    "definition": "Rust概念54说明",
    "category": "Rust",
    "tags": [
      "Rust"
    ],
    "updatedAt": "2026-07-03T00:00:00.000Z"
  },
  {
    "id": "rs-glossary-056",
    "term": "Rust概念55",
    "definition": "Rust概念55说明",
    "category": "Rust",
    "tags": [
      "Rust"
    ],
    "updatedAt": "2026-07-03T00:00:00.000Z"
  },
  {
    "id": "rs-glossary-057",
    "term": "Rust概念56",
    "definition": "Rust概念56说明",
    "category": "Rust",
    "tags": [
      "Rust"
    ],
    "updatedAt": "2026-07-03T00:00:00.000Z"
  },
  {
    "id": "rs-glossary-058",
    "term": "Rust概念57",
    "definition": "Rust概念57说明",
    "category": "Rust",
    "tags": [
      "Rust"
    ],
    "updatedAt": "2026-07-03T00:00:00.000Z"
  },
  {
    "id": "rs-glossary-059",
    "term": "Rust概念58",
    "definition": "Rust概念58说明",
    "category": "Rust",
    "tags": [
      "Rust"
    ],
    "updatedAt": "2026-07-03T00:00:00.000Z"
  },
  {
    "id": "rs-glossary-060",
    "term": "Rust概念59",
    "definition": "Rust概念59说明",
    "category": "Rust",
    "tags": [
      "Rust"
    ],
    "updatedAt": "2026-07-03T00:00:00.000Z"
  },
  {
    "id": "rs-glossary-061",
    "term": "Rust概念60",
    "definition": "Rust概念60说明",
    "category": "Rust",
    "tags": [
      "Rust"
    ],
    "updatedAt": "2026-07-03T00:00:00.000Z"
  },
  {
    "id": "rs-glossary-062",
    "term": "Rust概念61",
    "definition": "Rust概念61说明",
    "category": "Rust",
    "tags": [
      "Rust"
    ],
    "updatedAt": "2026-07-03T00:00:00.000Z"
  },
  {
    "id": "rs-glossary-063",
    "term": "Rust概念62",
    "definition": "Rust概念62说明",
    "category": "Rust",
    "tags": [
      "Rust"
    ],
    "updatedAt": "2026-07-03T00:00:00.000Z"
  },
  {
    "id": "rs-glossary-064",
    "term": "Rust概念63",
    "definition": "Rust概念63说明",
    "category": "Rust",
    "tags": [
      "Rust"
    ],
    "updatedAt": "2026-07-03T00:00:00.000Z"
  },
  {
    "id": "rs-glossary-065",
    "term": "Rust概念64",
    "definition": "Rust概念64说明",
    "category": "Rust",
    "tags": [
      "Rust"
    ],
    "updatedAt": "2026-07-03T00:00:00.000Z"
  },
  {
    "id": "rs-glossary-066",
    "term": "Rust概念65",
    "definition": "Rust概念65说明",
    "category": "Rust",
    "tags": [
      "Rust"
    ],
    "updatedAt": "2026-07-03T00:00:00.000Z"
  },
  {
    "id": "rs-glossary-067",
    "term": "Rust概念66",
    "definition": "Rust概念66说明",
    "category": "Rust",
    "tags": [
      "Rust"
    ],
    "updatedAt": "2026-07-03T00:00:00.000Z"
  },
  {
    "id": "rs-glossary-068",
    "term": "Rust概念67",
    "definition": "Rust概念67说明",
    "category": "Rust",
    "tags": [
      "Rust"
    ],
    "updatedAt": "2026-07-03T00:00:00.000Z"
  },
  {
    "id": "rs-glossary-069",
    "term": "Rust概念68",
    "definition": "Rust概念68说明",
    "category": "Rust",
    "tags": [
      "Rust"
    ],
    "updatedAt": "2026-07-03T00:00:00.000Z"
  },
  {
    "id": "rs-glossary-070",
    "term": "Rust概念69",
    "definition": "Rust概念69说明",
    "category": "Rust",
    "tags": [
      "Rust"
    ],
    "updatedAt": "2026-07-03T00:00:00.000Z"
  },
  {
    "id": "rs-glossary-071",
    "term": "Rust概念70",
    "definition": "Rust概念70说明",
    "category": "Rust",
    "tags": [
      "Rust"
    ],
    "updatedAt": "2026-07-03T00:00:00.000Z"
  },
  {
    "id": "rs-glossary-072",
    "term": "Rust概念71",
    "definition": "Rust概念71说明",
    "category": "Rust",
    "tags": [
      "Rust"
    ],
    "updatedAt": "2026-07-03T00:00:00.000Z"
  },
  {
    "id": "rs-glossary-073",
    "term": "Rust概念72",
    "definition": "Rust概念72说明",
    "category": "Rust",
    "tags": [
      "Rust"
    ],
    "updatedAt": "2026-07-03T00:00:00.000Z"
  },
  {
    "id": "rs-glossary-074",
    "term": "Rust概念73",
    "definition": "Rust概念73说明",
    "category": "Rust",
    "tags": [
      "Rust"
    ],
    "updatedAt": "2026-07-03T00:00:00.000Z"
  },
  {
    "id": "rs-glossary-075",
    "term": "Rust概念74",
    "definition": "Rust概念74说明",
    "category": "Rust",
    "tags": [
      "Rust"
    ],
    "updatedAt": "2026-07-03T00:00:00.000Z"
  },
  {
    "id": "rs-glossary-076",
    "term": "Rust概念75",
    "definition": "Rust概念75说明",
    "category": "Rust",
    "tags": [
      "Rust"
    ],
    "updatedAt": "2026-07-03T00:00:00.000Z"
  },
  {
    "id": "rs-glossary-077",
    "term": "Rust概念76",
    "definition": "Rust概念76说明",
    "category": "Rust",
    "tags": [
      "Rust"
    ],
    "updatedAt": "2026-07-03T00:00:00.000Z"
  },
  {
    "id": "rs-glossary-078",
    "term": "Rust概念77",
    "definition": "Rust概念77说明",
    "category": "Rust",
    "tags": [
      "Rust"
    ],
    "updatedAt": "2026-07-03T00:00:00.000Z"
  },
  {
    "id": "rs-glossary-079",
    "term": "Rust概念78",
    "definition": "Rust概念78说明",
    "category": "Rust",
    "tags": [
      "Rust"
    ],
    "updatedAt": "2026-07-03T00:00:00.000Z"
  },
  {
    "id": "rs-glossary-080",
    "term": "Rust概念79",
    "definition": "Rust概念79说明",
    "category": "Rust",
    "tags": [
      "Rust"
    ],
    "updatedAt": "2026-07-03T00:00:00.000Z"
  },
  {
    "id": "rs-glossary-081",
    "term": "Rust概念80",
    "definition": "Rust概念80说明",
    "category": "Rust",
    "tags": [
      "Rust"
    ],
    "updatedAt": "2026-07-03T00:00:00.000Z"
  },
  {
    "id": "rs-glossary-082",
    "term": "Rust概念81",
    "definition": "Rust概念81说明",
    "category": "Rust",
    "tags": [
      "Rust"
    ],
    "updatedAt": "2026-07-03T00:00:00.000Z"
  },
  {
    "id": "rs-glossary-083",
    "term": "Rust概念82",
    "definition": "Rust概念82说明",
    "category": "Rust",
    "tags": [
      "Rust"
    ],
    "updatedAt": "2026-07-03T00:00:00.000Z"
  },
  {
    "id": "rs-glossary-084",
    "term": "Rust概念83",
    "definition": "Rust概念83说明",
    "category": "Rust",
    "tags": [
      "Rust"
    ],
    "updatedAt": "2026-07-03T00:00:00.000Z"
  },
  {
    "id": "rs-glossary-085",
    "term": "Rust概念84",
    "definition": "Rust概念84说明",
    "category": "Rust",
    "tags": [
      "Rust"
    ],
    "updatedAt": "2026-07-03T00:00:00.000Z"
  },
  {
    "id": "rs-glossary-086",
    "term": "Rust概念85",
    "definition": "Rust概念85说明",
    "category": "Rust",
    "tags": [
      "Rust"
    ],
    "updatedAt": "2026-07-03T00:00:00.000Z"
  },
  {
    "id": "rs-glossary-087",
    "term": "Rust概念86",
    "definition": "Rust概念86说明",
    "category": "Rust",
    "tags": [
      "Rust"
    ],
    "updatedAt": "2026-07-03T00:00:00.000Z"
  },
  {
    "id": "rs-glossary-088",
    "term": "Rust概念87",
    "definition": "Rust概念87说明",
    "category": "Rust",
    "tags": [
      "Rust"
    ],
    "updatedAt": "2026-07-03T00:00:00.000Z"
  },
  {
    "id": "rs-glossary-089",
    "term": "Rust概念88",
    "definition": "Rust概念88说明",
    "category": "Rust",
    "tags": [
      "Rust"
    ],
    "updatedAt": "2026-07-03T00:00:00.000Z"
  },
  {
    "id": "rs-glossary-090",
    "term": "Rust概念89",
    "definition": "Rust概念89说明",
    "category": "Rust",
    "tags": [
      "Rust"
    ],
    "updatedAt": "2026-07-03T00:00:00.000Z"
  },
  {
    "id": "rs-glossary-091",
    "term": "Rust概念90",
    "definition": "Rust概念90说明",
    "category": "Rust",
    "tags": [
      "Rust"
    ],
    "updatedAt": "2026-07-03T00:00:00.000Z"
  },
  {
    "id": "rs-glossary-092",
    "term": "Rust概念91",
    "definition": "Rust概念91说明",
    "category": "Rust",
    "tags": [
      "Rust"
    ],
    "updatedAt": "2026-07-03T00:00:00.000Z"
  },
  {
    "id": "rs-glossary-093",
    "term": "Rust概念92",
    "definition": "Rust概念92说明",
    "category": "Rust",
    "tags": [
      "Rust"
    ],
    "updatedAt": "2026-07-03T00:00:00.000Z"
  },
  {
    "id": "rs-glossary-094",
    "term": "Rust概念93",
    "definition": "Rust概念93说明",
    "category": "Rust",
    "tags": [
      "Rust"
    ],
    "updatedAt": "2026-07-03T00:00:00.000Z"
  },
  {
    "id": "rs-glossary-095",
    "term": "Rust概念94",
    "definition": "Rust概念94说明",
    "category": "Rust",
    "tags": [
      "Rust"
    ],
    "updatedAt": "2026-07-03T00:00:00.000Z"
  },
  {
    "id": "rs-glossary-096",
    "term": "Rust概念95",
    "definition": "Rust概念95说明",
    "category": "Rust",
    "tags": [
      "Rust"
    ],
    "updatedAt": "2026-07-03T00:00:00.000Z"
  },
  {
    "id": "rs-glossary-097",
    "term": "Rust概念96",
    "definition": "Rust概念96说明",
    "category": "Rust",
    "tags": [
      "Rust"
    ],
    "updatedAt": "2026-07-03T00:00:00.000Z"
  },
  {
    "id": "rs-glossary-098",
    "term": "Rust概念97",
    "definition": "Rust概念97说明",
    "category": "Rust",
    "tags": [
      "Rust"
    ],
    "updatedAt": "2026-07-03T00:00:00.000Z"
  },
  {
    "id": "rs-glossary-099",
    "term": "Rust概念98",
    "definition": "Rust概念98说明",
    "category": "Rust",
    "tags": [
      "Rust"
    ],
    "updatedAt": "2026-07-03T00:00:00.000Z"
  },
  {
    "id": "rs-glossary-100",
    "term": "Rust概念99",
    "definition": "Rust概念99说明",
    "category": "Rust",
    "tags": [
      "Rust"
    ],
    "updatedAt": "2026-07-03T00:00:00.000Z"
  },
  {
    "id": "rs-glossary-101",
    "term": "Rust概念100",
    "definition": "Rust概念100说明",
    "category": "Rust",
    "tags": [
      "Rust"
    ],
    "updatedAt": "2026-07-03T00:00:00.000Z"
  },
  {
    "id": "rs-glossary-102",
    "term": "Rust概念101",
    "definition": "Rust概念101说明",
    "category": "Rust",
    "tags": [
      "Rust"
    ],
    "updatedAt": "2026-07-03T00:00:00.000Z"
  },
  {
    "id": "rs-glossary-103",
    "term": "Rust概念102",
    "definition": "Rust概念102说明",
    "category": "Rust",
    "tags": [
      "Rust"
    ],
    "updatedAt": "2026-07-03T00:00:00.000Z"
  },
  {
    "id": "rs-glossary-104",
    "term": "Rust概念103",
    "definition": "Rust概念103说明",
    "category": "Rust",
    "tags": [
      "Rust"
    ],
    "updatedAt": "2026-07-03T00:00:00.000Z"
  },
  {
    "id": "rs-glossary-105",
    "term": "Rust概念104",
    "definition": "Rust概念104说明",
    "category": "Rust",
    "tags": [
      "Rust"
    ],
    "updatedAt": "2026-07-03T00:00:00.000Z"
  },
  {
    "id": "rs-glossary-106",
    "term": "Rust概念105",
    "definition": "Rust概念105说明",
    "category": "Rust",
    "tags": [
      "Rust"
    ],
    "updatedAt": "2026-07-03T00:00:00.000Z"
  },
  {
    "id": "rs-glossary-107",
    "term": "Rust概念106",
    "definition": "Rust概念106说明",
    "category": "Rust",
    "tags": [
      "Rust"
    ],
    "updatedAt": "2026-07-03T00:00:00.000Z"
  },
  {
    "id": "rs-glossary-108",
    "term": "Rust概念107",
    "definition": "Rust概念107说明",
    "category": "Rust",
    "tags": [
      "Rust"
    ],
    "updatedAt": "2026-07-03T00:00:00.000Z"
  },
  {
    "id": "rs-glossary-109",
    "term": "Rust概念108",
    "definition": "Rust概念108说明",
    "category": "Rust",
    "tags": [
      "Rust"
    ],
    "updatedAt": "2026-07-03T00:00:00.000Z"
  },
  {
    "id": "rs-glossary-110",
    "term": "Rust概念109",
    "definition": "Rust概念109说明",
    "category": "Rust",
    "tags": [
      "Rust"
    ],
    "updatedAt": "2026-07-03T00:00:00.000Z"
  },
  {
    "id": "rs-glossary-111",
    "term": "Rust概念110",
    "definition": "Rust概念110说明",
    "category": "Rust",
    "tags": [
      "Rust"
    ],
    "updatedAt": "2026-07-03T00:00:00.000Z"
  },
  {
    "id": "rs-glossary-112",
    "term": "Rust概念111",
    "definition": "Rust概念111说明",
    "category": "Rust",
    "tags": [
      "Rust"
    ],
    "updatedAt": "2026-07-03T00:00:00.000Z"
  },
  {
    "id": "rs-glossary-113",
    "term": "Rust概念112",
    "definition": "Rust概念112说明",
    "category": "Rust",
    "tags": [
      "Rust"
    ],
    "updatedAt": "2026-07-03T00:00:00.000Z"
  },
  {
    "id": "rs-glossary-114",
    "term": "Rust概念113",
    "definition": "Rust概念113说明",
    "category": "Rust",
    "tags": [
      "Rust"
    ],
    "updatedAt": "2026-07-03T00:00:00.000Z"
  },
  {
    "id": "rs-glossary-115",
    "term": "Rust概念114",
    "definition": "Rust概念114说明",
    "category": "Rust",
    "tags": [
      "Rust"
    ],
    "updatedAt": "2026-07-03T00:00:00.000Z"
  },
  {
    "id": "rs-glossary-116",
    "term": "Rust概念115",
    "definition": "Rust概念115说明",
    "category": "Rust",
    "tags": [
      "Rust"
    ],
    "updatedAt": "2026-07-03T00:00:00.000Z"
  },
  {
    "id": "rs-glossary-117",
    "term": "Rust概念116",
    "definition": "Rust概念116说明",
    "category": "Rust",
    "tags": [
      "Rust"
    ],
    "updatedAt": "2026-07-03T00:00:00.000Z"
  },
  {
    "id": "rs-glossary-118",
    "term": "Rust概念117",
    "definition": "Rust概念117说明",
    "category": "Rust",
    "tags": [
      "Rust"
    ],
    "updatedAt": "2026-07-03T00:00:00.000Z"
  },
  {
    "id": "rs-glossary-119",
    "term": "Rust概念118",
    "definition": "Rust概念118说明",
    "category": "Rust",
    "tags": [
      "Rust"
    ],
    "updatedAt": "2026-07-03T00:00:00.000Z"
  },
  {
    "id": "rs-glossary-120",
    "term": "Rust概念119",
    "definition": "Rust概念119说明",
    "category": "Rust",
    "tags": [
      "Rust"
    ],
    "updatedAt": "2026-07-03T00:00:00.000Z"
  },
  {
    "id": "rs-glossary-121",
    "term": "Rust概念120",
    "definition": "Rust概念120说明",
    "category": "Rust",
    "tags": [
      "Rust"
    ],
    "updatedAt": "2026-07-03T00:00:00.000Z"
  },
  {
    "id": "rs-glossary-122",
    "term": "Rust概念121",
    "definition": "Rust概念121说明",
    "category": "Rust",
    "tags": [
      "Rust"
    ],
    "updatedAt": "2026-07-03T00:00:00.000Z"
  },
  {
    "id": "rs-glossary-123",
    "term": "Rust概念122",
    "definition": "Rust概念122说明",
    "category": "Rust",
    "tags": [
      "Rust"
    ],
    "updatedAt": "2026-07-03T00:00:00.000Z"
  },
  {
    "id": "rs-glossary-124",
    "term": "Rust概念123",
    "definition": "Rust概念123说明",
    "category": "Rust",
    "tags": [
      "Rust"
    ],
    "updatedAt": "2026-07-03T00:00:00.000Z"
  },
  {
    "id": "rs-glossary-125",
    "term": "Rust概念124",
    "definition": "Rust概念124说明",
    "category": "Rust",
    "tags": [
      "Rust"
    ],
    "updatedAt": "2026-07-03T00:00:00.000Z"
  },
  {
    "id": "rs-glossary-126",
    "term": "Rust概念125",
    "definition": "Rust概念125说明",
    "category": "Rust",
    "tags": [
      "Rust"
    ],
    "updatedAt": "2026-07-03T00:00:00.000Z"
  },
  {
    "id": "rs-glossary-127",
    "term": "Rust概念126",
    "definition": "Rust概念126说明",
    "category": "Rust",
    "tags": [
      "Rust"
    ],
    "updatedAt": "2026-07-03T00:00:00.000Z"
  },
  {
    "id": "rs-glossary-128",
    "term": "Rust概念127",
    "definition": "Rust概念127说明",
    "category": "Rust",
    "tags": [
      "Rust"
    ],
    "updatedAt": "2026-07-03T00:00:00.000Z"
  },
  {
    "id": "rs-glossary-129",
    "term": "Rust概念128",
    "definition": "Rust概念128说明",
    "category": "Rust",
    "tags": [
      "Rust"
    ],
    "updatedAt": "2026-07-03T00:00:00.000Z"
  },
  {
    "id": "rs-glossary-130",
    "term": "Rust概念129",
    "definition": "Rust概念129说明",
    "category": "Rust",
    "tags": [
      "Rust"
    ],
    "updatedAt": "2026-07-03T00:00:00.000Z"
  },
  {
    "id": "rs-glossary-131",
    "term": "Rust概念130",
    "definition": "Rust概念130说明",
    "category": "Rust",
    "tags": [
      "Rust"
    ],
    "updatedAt": "2026-07-03T00:00:00.000Z"
  },
  {
    "id": "rs-glossary-132",
    "term": "Rust概念131",
    "definition": "Rust概念131说明",
    "category": "Rust",
    "tags": [
      "Rust"
    ],
    "updatedAt": "2026-07-03T00:00:00.000Z"
  },
  {
    "id": "rs-glossary-133",
    "term": "Rust概念132",
    "definition": "Rust概念132说明",
    "category": "Rust",
    "tags": [
      "Rust"
    ],
    "updatedAt": "2026-07-03T00:00:00.000Z"
  },
  {
    "id": "rs-glossary-134",
    "term": "Rust概念133",
    "definition": "Rust概念133说明",
    "category": "Rust",
    "tags": [
      "Rust"
    ],
    "updatedAt": "2026-07-03T00:00:00.000Z"
  },
  {
    "id": "rs-glossary-135",
    "term": "Rust概念134",
    "definition": "Rust概念134说明",
    "category": "Rust",
    "tags": [
      "Rust"
    ],
    "updatedAt": "2026-07-03T00:00:00.000Z"
  },
  {
    "id": "rs-glossary-136",
    "term": "Rust概念135",
    "definition": "Rust概念135说明",
    "category": "Rust",
    "tags": [
      "Rust"
    ],
    "updatedAt": "2026-07-03T00:00:00.000Z"
  },
  {
    "id": "rs-glossary-137",
    "term": "Rust概念136",
    "definition": "Rust概念136说明",
    "category": "Rust",
    "tags": [
      "Rust"
    ],
    "updatedAt": "2026-07-03T00:00:00.000Z"
  },
  {
    "id": "rs-glossary-138",
    "term": "Rust概念137",
    "definition": "Rust概念137说明",
    "category": "Rust",
    "tags": [
      "Rust"
    ],
    "updatedAt": "2026-07-03T00:00:00.000Z"
  },
  {
    "id": "rs-glossary-139",
    "term": "Rust概念138",
    "definition": "Rust概念138说明",
    "category": "Rust",
    "tags": [
      "Rust"
    ],
    "updatedAt": "2026-07-03T00:00:00.000Z"
  },
  {
    "id": "rs-glossary-140",
    "term": "Rust概念139",
    "definition": "Rust概念139说明",
    "category": "Rust",
    "tags": [
      "Rust"
    ],
    "updatedAt": "2026-07-03T00:00:00.000Z"
  },
  {
    "id": "rs-glossary-141",
    "term": "Rust概念140",
    "definition": "Rust概念140说明",
    "category": "Rust",
    "tags": [
      "Rust"
    ],
    "updatedAt": "2026-07-03T00:00:00.000Z"
  },
  {
    "id": "rs-glossary-142",
    "term": "Rust概念141",
    "definition": "Rust概念141说明",
    "category": "Rust",
    "tags": [
      "Rust"
    ],
    "updatedAt": "2026-07-03T00:00:00.000Z"
  },
  {
    "id": "rs-glossary-143",
    "term": "Rust概念142",
    "definition": "Rust概念142说明",
    "category": "Rust",
    "tags": [
      "Rust"
    ],
    "updatedAt": "2026-07-03T00:00:00.000Z"
  },
  {
    "id": "rs-glossary-144",
    "term": "Rust概念143",
    "definition": "Rust概念143说明",
    "category": "Rust",
    "tags": [
      "Rust"
    ],
    "updatedAt": "2026-07-03T00:00:00.000Z"
  },
  {
    "id": "rs-glossary-145",
    "term": "Rust概念144",
    "definition": "Rust概念144说明",
    "category": "Rust",
    "tags": [
      "Rust"
    ],
    "updatedAt": "2026-07-03T00:00:00.000Z"
  },
  {
    "id": "rs-glossary-146",
    "term": "Rust概念145",
    "definition": "Rust概念145说明",
    "category": "Rust",
    "tags": [
      "Rust"
    ],
    "updatedAt": "2026-07-03T00:00:00.000Z"
  },
  {
    "id": "rs-glossary-147",
    "term": "Rust概念146",
    "definition": "Rust概念146说明",
    "category": "Rust",
    "tags": [
      "Rust"
    ],
    "updatedAt": "2026-07-03T00:00:00.000Z"
  },
  {
    "id": "rs-glossary-148",
    "term": "Rust概念147",
    "definition": "Rust概念147说明",
    "category": "Rust",
    "tags": [
      "Rust"
    ],
    "updatedAt": "2026-07-03T00:00:00.000Z"
  },
  {
    "id": "rs-glossary-149",
    "term": "Rust概念148",
    "definition": "Rust概念148说明",
    "category": "Rust",
    "tags": [
      "Rust"
    ],
    "updatedAt": "2026-07-03T00:00:00.000Z"
  },
  {
    "id": "rs-glossary-150",
    "term": "Rust概念149",
    "definition": "Rust概念149说明",
    "category": "Rust",
    "tags": [
      "Rust"
    ],
    "updatedAt": "2026-07-03T00:00:00.000Z"
  },
  {
    "id": "rs-glossary-151",
    "term": "Rust概念150",
    "definition": "Rust概念150说明",
    "category": "Rust",
    "tags": [
      "Rust"
    ],
    "updatedAt": "2026-07-03T00:00:00.000Z"
  },
  {
    "id": "rs-glossary-152",
    "term": "Rust概念151",
    "definition": "Rust概念151说明",
    "category": "Rust",
    "tags": [
      "Rust"
    ],
    "updatedAt": "2026-07-03T00:00:00.000Z"
  },
  {
    "id": "rs-glossary-153",
    "term": "Rust概念152",
    "definition": "Rust概念152说明",
    "category": "Rust",
    "tags": [
      "Rust"
    ],
    "updatedAt": "2026-07-03T00:00:00.000Z"
  },
  {
    "id": "rs-glossary-154",
    "term": "Rust概念153",
    "definition": "Rust概念153说明",
    "category": "Rust",
    "tags": [
      "Rust"
    ],
    "updatedAt": "2026-07-03T00:00:00.000Z"
  },
  {
    "id": "rs-glossary-155",
    "term": "Rust概念154",
    "definition": "Rust概念154说明",
    "category": "Rust",
    "tags": [
      "Rust"
    ],
    "updatedAt": "2026-07-03T00:00:00.000Z"
  },
  {
    "id": "rs-glossary-156",
    "term": "Rust概念155",
    "definition": "Rust概念155说明",
    "category": "Rust",
    "tags": [
      "Rust"
    ],
    "updatedAt": "2026-07-03T00:00:00.000Z"
  },
  {
    "id": "rs-glossary-157",
    "term": "Rust概念156",
    "definition": "Rust概念156说明",
    "category": "Rust",
    "tags": [
      "Rust"
    ],
    "updatedAt": "2026-07-03T00:00:00.000Z"
  },
  {
    "id": "rs-glossary-158",
    "term": "Rust概念157",
    "definition": "Rust概念157说明",
    "category": "Rust",
    "tags": [
      "Rust"
    ],
    "updatedAt": "2026-07-03T00:00:00.000Z"
  },
  {
    "id": "rs-glossary-159",
    "term": "Rust概念158",
    "definition": "Rust概念158说明",
    "category": "Rust",
    "tags": [
      "Rust"
    ],
    "updatedAt": "2026-07-03T00:00:00.000Z"
  },
  {
    "id": "rs-glossary-160",
    "term": "Rust概念159",
    "definition": "Rust概念159说明",
    "category": "Rust",
    "tags": [
      "Rust"
    ],
    "updatedAt": "2026-07-03T00:00:00.000Z"
  },
  {
    "id": "rs-glossary-161",
    "term": "Rust概念160",
    "definition": "Rust概念160说明",
    "category": "Rust",
    "tags": [
      "Rust"
    ],
    "updatedAt": "2026-07-03T00:00:00.000Z"
  },
  {
    "id": "rs-glossary-162",
    "term": "Rust概念161",
    "definition": "Rust概念161说明",
    "category": "Rust",
    "tags": [
      "Rust"
    ],
    "updatedAt": "2026-07-03T00:00:00.000Z"
  },
  {
    "id": "rs-glossary-163",
    "term": "Rust概念162",
    "definition": "Rust概念162说明",
    "category": "Rust",
    "tags": [
      "Rust"
    ],
    "updatedAt": "2026-07-03T00:00:00.000Z"
  },
  {
    "id": "rs-glossary-164",
    "term": "Rust概念163",
    "definition": "Rust概念163说明",
    "category": "Rust",
    "tags": [
      "Rust"
    ],
    "updatedAt": "2026-07-03T00:00:00.000Z"
  },
  {
    "id": "rs-glossary-165",
    "term": "Rust概念164",
    "definition": "Rust概念164说明",
    "category": "Rust",
    "tags": [
      "Rust"
    ],
    "updatedAt": "2026-07-03T00:00:00.000Z"
  },
  {
    "id": "rs-glossary-166",
    "term": "Rust概念165",
    "definition": "Rust概念165说明",
    "category": "Rust",
    "tags": [
      "Rust"
    ],
    "updatedAt": "2026-07-03T00:00:00.000Z"
  },
  {
    "id": "rs-glossary-167",
    "term": "Rust概念166",
    "definition": "Rust概念166说明",
    "category": "Rust",
    "tags": [
      "Rust"
    ],
    "updatedAt": "2026-07-03T00:00:00.000Z"
  },
  {
    "id": "rs-glossary-168",
    "term": "Rust概念167",
    "definition": "Rust概念167说明",
    "category": "Rust",
    "tags": [
      "Rust"
    ],
    "updatedAt": "2026-07-03T00:00:00.000Z"
  },
  {
    "id": "rs-glossary-169",
    "term": "Rust概念168",
    "definition": "Rust概念168说明",
    "category": "Rust",
    "tags": [
      "Rust"
    ],
    "updatedAt": "2026-07-03T00:00:00.000Z"
  },
  {
    "id": "rs-glossary-170",
    "term": "Rust概念169",
    "definition": "Rust概念169说明",
    "category": "Rust",
    "tags": [
      "Rust"
    ],
    "updatedAt": "2026-07-03T00:00:00.000Z"
  },
  {
    "id": "rs-glossary-171",
    "term": "Rust概念170",
    "definition": "Rust概念170说明",
    "category": "Rust",
    "tags": [
      "Rust"
    ],
    "updatedAt": "2026-07-03T00:00:00.000Z"
  },
  {
    "id": "rs-glossary-172",
    "term": "Rust概念171",
    "definition": "Rust概念171说明",
    "category": "Rust",
    "tags": [
      "Rust"
    ],
    "updatedAt": "2026-07-03T00:00:00.000Z"
  },
  {
    "id": "rs-glossary-173",
    "term": "Rust概念172",
    "definition": "Rust概念172说明",
    "category": "Rust",
    "tags": [
      "Rust"
    ],
    "updatedAt": "2026-07-03T00:00:00.000Z"
  },
  {
    "id": "rs-glossary-174",
    "term": "Rust概念173",
    "definition": "Rust概念173说明",
    "category": "Rust",
    "tags": [
      "Rust"
    ],
    "updatedAt": "2026-07-03T00:00:00.000Z"
  },
  {
    "id": "rs-glossary-175",
    "term": "Rust概念174",
    "definition": "Rust概念174说明",
    "category": "Rust",
    "tags": [
      "Rust"
    ],
    "updatedAt": "2026-07-03T00:00:00.000Z"
  },
  {
    "id": "rs-glossary-176",
    "term": "Rust概念175",
    "definition": "Rust概念175说明",
    "category": "Rust",
    "tags": [
      "Rust"
    ],
    "updatedAt": "2026-07-03T00:00:00.000Z"
  },
  {
    "id": "rs-glossary-177",
    "term": "Rust概念176",
    "definition": "Rust概念176说明",
    "category": "Rust",
    "tags": [
      "Rust"
    ],
    "updatedAt": "2026-07-03T00:00:00.000Z"
  },
  {
    "id": "rs-glossary-178",
    "term": "Rust概念177",
    "definition": "Rust概念177说明",
    "category": "Rust",
    "tags": [
      "Rust"
    ],
    "updatedAt": "2026-07-03T00:00:00.000Z"
  },
  {
    "id": "rs-glossary-179",
    "term": "Rust概念178",
    "definition": "Rust概念178说明",
    "category": "Rust",
    "tags": [
      "Rust"
    ],
    "updatedAt": "2026-07-03T00:00:00.000Z"
  },
  {
    "id": "rs-glossary-180",
    "term": "Rust概念179",
    "definition": "Rust概念179说明",
    "category": "Rust",
    "tags": [
      "Rust"
    ],
    "updatedAt": "2026-07-03T00:00:00.000Z"
  },
  {
    "id": "rs-glossary-181",
    "term": "Rust概念180",
    "definition": "Rust概念180说明",
    "category": "Rust",
    "tags": [
      "Rust"
    ],
    "updatedAt": "2026-07-03T00:00:00.000Z"
  },
  {
    "id": "rs-glossary-182",
    "term": "Rust概念181",
    "definition": "Rust概念181说明",
    "category": "Rust",
    "tags": [
      "Rust"
    ],
    "updatedAt": "2026-07-03T00:00:00.000Z"
  },
  {
    "id": "rs-glossary-183",
    "term": "Rust概念182",
    "definition": "Rust概念182说明",
    "category": "Rust",
    "tags": [
      "Rust"
    ],
    "updatedAt": "2026-07-03T00:00:00.000Z"
  },
  {
    "id": "rs-glossary-184",
    "term": "Rust概念183",
    "definition": "Rust概念183说明",
    "category": "Rust",
    "tags": [
      "Rust"
    ],
    "updatedAt": "2026-07-03T00:00:00.000Z"
  },
  {
    "id": "rs-glossary-185",
    "term": "Rust概念184",
    "definition": "Rust概念184说明",
    "category": "Rust",
    "tags": [
      "Rust"
    ],
    "updatedAt": "2026-07-03T00:00:00.000Z"
  },
  {
    "id": "rs-glossary-186",
    "term": "Rust概念185",
    "definition": "Rust概念185说明",
    "category": "Rust",
    "tags": [
      "Rust"
    ],
    "updatedAt": "2026-07-03T00:00:00.000Z"
  },
  {
    "id": "rs-glossary-187",
    "term": "Rust概念186",
    "definition": "Rust概念186说明",
    "category": "Rust",
    "tags": [
      "Rust"
    ],
    "updatedAt": "2026-07-03T00:00:00.000Z"
  },
  {
    "id": "rs-glossary-188",
    "term": "Rust概念187",
    "definition": "Rust概念187说明",
    "category": "Rust",
    "tags": [
      "Rust"
    ],
    "updatedAt": "2026-07-03T00:00:00.000Z"
  },
  {
    "id": "rs-glossary-189",
    "term": "Rust概念188",
    "definition": "Rust概念188说明",
    "category": "Rust",
    "tags": [
      "Rust"
    ],
    "updatedAt": "2026-07-03T00:00:00.000Z"
  },
  {
    "id": "rs-glossary-190",
    "term": "Rust概念189",
    "definition": "Rust概念189说明",
    "category": "Rust",
    "tags": [
      "Rust"
    ],
    "updatedAt": "2026-07-03T00:00:00.000Z"
  },
  {
    "id": "rs-glossary-191",
    "term": "Rust概念190",
    "definition": "Rust概念190说明",
    "category": "Rust",
    "tags": [
      "Rust"
    ],
    "updatedAt": "2026-07-03T00:00:00.000Z"
  },
  {
    "id": "rs-glossary-192",
    "term": "Rust概念191",
    "definition": "Rust概念191说明",
    "category": "Rust",
    "tags": [
      "Rust"
    ],
    "updatedAt": "2026-07-03T00:00:00.000Z"
  },
  {
    "id": "rs-glossary-193",
    "term": "Rust概念192",
    "definition": "Rust概念192说明",
    "category": "Rust",
    "tags": [
      "Rust"
    ],
    "updatedAt": "2026-07-03T00:00:00.000Z"
  },
  {
    "id": "rs-glossary-194",
    "term": "Rust概念193",
    "definition": "Rust概念193说明",
    "category": "Rust",
    "tags": [
      "Rust"
    ],
    "updatedAt": "2026-07-03T00:00:00.000Z"
  },
  {
    "id": "rs-glossary-195",
    "term": "Rust概念194",
    "definition": "Rust概念194说明",
    "category": "Rust",
    "tags": [
      "Rust"
    ],
    "updatedAt": "2026-07-03T00:00:00.000Z"
  },
  {
    "id": "rs-glossary-196",
    "term": "Rust概念195",
    "definition": "Rust概念195说明",
    "category": "Rust",
    "tags": [
      "Rust"
    ],
    "updatedAt": "2026-07-03T00:00:00.000Z"
  },
  {
    "id": "rs-glossary-197",
    "term": "Rust概念196",
    "definition": "Rust概念196说明",
    "category": "Rust",
    "tags": [
      "Rust"
    ],
    "updatedAt": "2026-07-03T00:00:00.000Z"
  },
  {
    "id": "rs-glossary-198",
    "term": "Rust概念197",
    "definition": "Rust概念197说明",
    "category": "Rust",
    "tags": [
      "Rust"
    ],
    "updatedAt": "2026-07-03T00:00:00.000Z"
  },
  {
    "id": "rs-glossary-199",
    "term": "Rust概念198",
    "definition": "Rust概念198说明",
    "category": "Rust",
    "tags": [
      "Rust"
    ],
    "updatedAt": "2026-07-03T00:00:00.000Z"
  },
  {
    "id": "rs-glossary-200",
    "term": "Rust概念199",
    "definition": "Rust概念199说明",
    "category": "Rust",
    "tags": [
      "Rust"
    ],
    "updatedAt": "2026-07-03T00:00:00.000Z"
  },
  {
    "id": "rs-glossary-201",
    "term": "Rust概念200",
    "definition": "Rust概念200说明",
    "category": "Rust",
    "tags": [
      "Rust"
    ],
    "updatedAt": "2026-07-03T00:00:00.000Z"
  },
  {
    "id": "rs-glossary-202",
    "term": "Rust概念201",
    "definition": "Rust概念201说明",
    "category": "Rust",
    "tags": [
      "Rust"
    ],
    "updatedAt": "2026-07-03T00:00:00.000Z"
  },
  {
    "id": "rs-glossary-203",
    "term": "Rust概念202",
    "definition": "Rust概念202说明",
    "category": "Rust",
    "tags": [
      "Rust"
    ],
    "updatedAt": "2026-07-03T00:00:00.000Z"
  },
  {
    "id": "rs-glossary-204",
    "term": "Rust概念203",
    "definition": "Rust概念203说明",
    "category": "Rust",
    "tags": [
      "Rust"
    ],
    "updatedAt": "2026-07-03T00:00:00.000Z"
  },
  {
    "id": "rs-glossary-205",
    "term": "Rust概念204",
    "definition": "Rust概念204说明",
    "category": "Rust",
    "tags": [
      "Rust"
    ],
    "updatedAt": "2026-07-03T00:00:00.000Z"
  },
  {
    "id": "rs-glossary-206",
    "term": "Rust概念205",
    "definition": "Rust概念205说明",
    "category": "Rust",
    "tags": [
      "Rust"
    ],
    "updatedAt": "2026-07-03T00:00:00.000Z"
  },
  {
    "id": "rs-glossary-207",
    "term": "Rust概念206",
    "definition": "Rust概念206说明",
    "category": "Rust",
    "tags": [
      "Rust"
    ],
    "updatedAt": "2026-07-03T00:00:00.000Z"
  },
  {
    "id": "rs-glossary-208",
    "term": "Rust概念207",
    "definition": "Rust概念207说明",
    "category": "Rust",
    "tags": [
      "Rust"
    ],
    "updatedAt": "2026-07-03T00:00:00.000Z"
  },
  {
    "id": "rs-glossary-209",
    "term": "Rust概念208",
    "definition": "Rust概念208说明",
    "category": "Rust",
    "tags": [
      "Rust"
    ],
    "updatedAt": "2026-07-03T00:00:00.000Z"
  },
  {
    "id": "rs-glossary-210",
    "term": "Rust概念209",
    "definition": "Rust概念209说明",
    "category": "Rust",
    "tags": [
      "Rust"
    ],
    "updatedAt": "2026-07-03T00:00:00.000Z"
  },
  {
    "id": "rs-glossary-211",
    "term": "Rust概念210",
    "definition": "Rust概念210说明",
    "category": "Rust",
    "tags": [
      "Rust"
    ],
    "updatedAt": "2026-07-03T00:00:00.000Z"
  },
  {
    "id": "rs-glossary-212",
    "term": "Rust概念211",
    "definition": "Rust概念211说明",
    "category": "Rust",
    "tags": [
      "Rust"
    ],
    "updatedAt": "2026-07-03T00:00:00.000Z"
  },
  {
    "id": "rs-glossary-213",
    "term": "Rust概念212",
    "definition": "Rust概念212说明",
    "category": "Rust",
    "tags": [
      "Rust"
    ],
    "updatedAt": "2026-07-03T00:00:00.000Z"
  },
  {
    "id": "rs-glossary-214",
    "term": "Rust概念213",
    "definition": "Rust概念213说明",
    "category": "Rust",
    "tags": [
      "Rust"
    ],
    "updatedAt": "2026-07-03T00:00:00.000Z"
  },
  {
    "id": "rs-glossary-215",
    "term": "Rust概念214",
    "definition": "Rust概念214说明",
    "category": "Rust",
    "tags": [
      "Rust"
    ],
    "updatedAt": "2026-07-03T00:00:00.000Z"
  },
  {
    "id": "rs-glossary-216",
    "term": "Rust概念215",
    "definition": "Rust概念215说明",
    "category": "Rust",
    "tags": [
      "Rust"
    ],
    "updatedAt": "2026-07-03T00:00:00.000Z"
  },
  {
    "id": "rs-glossary-217",
    "term": "Rust概念216",
    "definition": "Rust概念216说明",
    "category": "Rust",
    "tags": [
      "Rust"
    ],
    "updatedAt": "2026-07-03T00:00:00.000Z"
  },
  {
    "id": "rs-glossary-218",
    "term": "Rust概念217",
    "definition": "Rust概念217说明",
    "category": "Rust",
    "tags": [
      "Rust"
    ],
    "updatedAt": "2026-07-03T00:00:00.000Z"
  },
  {
    "id": "rs-glossary-219",
    "term": "Rust概念218",
    "definition": "Rust概念218说明",
    "category": "Rust",
    "tags": [
      "Rust"
    ],
    "updatedAt": "2026-07-03T00:00:00.000Z"
  },
  {
    "id": "rs-glossary-220",
    "term": "Rust概念219",
    "definition": "Rust概念219说明",
    "category": "Rust",
    "tags": [
      "Rust"
    ],
    "updatedAt": "2026-07-03T00:00:00.000Z"
  },
  {
    "id": "rs-glossary-221",
    "term": "Rust概念220",
    "definition": "Rust概念220说明",
    "category": "Rust",
    "tags": [
      "Rust"
    ],
    "updatedAt": "2026-07-03T00:00:00.000Z"
  },
  {
    "id": "rs-glossary-222",
    "term": "Rust概念221",
    "definition": "Rust概念221说明",
    "category": "Rust",
    "tags": [
      "Rust"
    ],
    "updatedAt": "2026-07-03T00:00:00.000Z"
  },
  {
    "id": "rs-glossary-223",
    "term": "Rust概念222",
    "definition": "Rust概念222说明",
    "category": "Rust",
    "tags": [
      "Rust"
    ],
    "updatedAt": "2026-07-03T00:00:00.000Z"
  },
  {
    "id": "rs-glossary-224",
    "term": "Rust概念223",
    "definition": "Rust概念223说明",
    "category": "Rust",
    "tags": [
      "Rust"
    ],
    "updatedAt": "2026-07-03T00:00:00.000Z"
  },
  {
    "id": "rs-glossary-225",
    "term": "Rust概念224",
    "definition": "Rust概念224说明",
    "category": "Rust",
    "tags": [
      "Rust"
    ],
    "updatedAt": "2026-07-03T00:00:00.000Z"
  },
  {
    "id": "rs-glossary-226",
    "term": "Rust概念225",
    "definition": "Rust概念225说明",
    "category": "Rust",
    "tags": [
      "Rust"
    ],
    "updatedAt": "2026-07-03T00:00:00.000Z"
  },
  {
    "id": "rs-glossary-227",
    "term": "Rust概念226",
    "definition": "Rust概念226说明",
    "category": "Rust",
    "tags": [
      "Rust"
    ],
    "updatedAt": "2026-07-03T00:00:00.000Z"
  },
  {
    "id": "rs-glossary-228",
    "term": "Rust概念227",
    "definition": "Rust概念227说明",
    "category": "Rust",
    "tags": [
      "Rust"
    ],
    "updatedAt": "2026-07-03T00:00:00.000Z"
  },
  {
    "id": "rs-glossary-229",
    "term": "Rust概念228",
    "definition": "Rust概念228说明",
    "category": "Rust",
    "tags": [
      "Rust"
    ],
    "updatedAt": "2026-07-03T00:00:00.000Z"
  },
  {
    "id": "rs-glossary-230",
    "term": "Rust概念229",
    "definition": "Rust概念229说明",
    "category": "Rust",
    "tags": [
      "Rust"
    ],
    "updatedAt": "2026-07-03T00:00:00.000Z"
  },
  {
    "id": "rs-glossary-231",
    "term": "Rust概念230",
    "definition": "Rust概念230说明",
    "category": "Rust",
    "tags": [
      "Rust"
    ],
    "updatedAt": "2026-07-03T00:00:00.000Z"
  },
  {
    "id": "rs-glossary-232",
    "term": "Rust概念231",
    "definition": "Rust概念231说明",
    "category": "Rust",
    "tags": [
      "Rust"
    ],
    "updatedAt": "2026-07-03T00:00:00.000Z"
  },
  {
    "id": "rs-glossary-233",
    "term": "Rust概念232",
    "definition": "Rust概念232说明",
    "category": "Rust",
    "tags": [
      "Rust"
    ],
    "updatedAt": "2026-07-03T00:00:00.000Z"
  },
  {
    "id": "rs-glossary-234",
    "term": "Rust概念233",
    "definition": "Rust概念233说明",
    "category": "Rust",
    "tags": [
      "Rust"
    ],
    "updatedAt": "2026-07-03T00:00:00.000Z"
  },
  {
    "id": "rs-glossary-235",
    "term": "Rust概念234",
    "definition": "Rust概念234说明",
    "category": "Rust",
    "tags": [
      "Rust"
    ],
    "updatedAt": "2026-07-03T00:00:00.000Z"
  },
  {
    "id": "rs-glossary-236",
    "term": "Rust概念235",
    "definition": "Rust概念235说明",
    "category": "Rust",
    "tags": [
      "Rust"
    ],
    "updatedAt": "2026-07-03T00:00:00.000Z"
  },
  {
    "id": "rs-glossary-237",
    "term": "Rust概念236",
    "definition": "Rust概念236说明",
    "category": "Rust",
    "tags": [
      "Rust"
    ],
    "updatedAt": "2026-07-03T00:00:00.000Z"
  },
  {
    "id": "rs-glossary-238",
    "term": "Rust概念237",
    "definition": "Rust概念237说明",
    "category": "Rust",
    "tags": [
      "Rust"
    ],
    "updatedAt": "2026-07-03T00:00:00.000Z"
  },
  {
    "id": "rs-glossary-239",
    "term": "Rust概念238",
    "definition": "Rust概念238说明",
    "category": "Rust",
    "tags": [
      "Rust"
    ],
    "updatedAt": "2026-07-03T00:00:00.000Z"
  },
  {
    "id": "rs-glossary-240",
    "term": "Rust概念239",
    "definition": "Rust概念239说明",
    "category": "Rust",
    "tags": [
      "Rust"
    ],
    "updatedAt": "2026-07-03T00:00:00.000Z"
  },
  {
    "id": "rs-glossary-241",
    "term": "Rust概念240",
    "definition": "Rust概念240说明",
    "category": "Rust",
    "tags": [
      "Rust"
    ],
    "updatedAt": "2026-07-03T00:00:00.000Z"
  },
  {
    "id": "rs-glossary-242",
    "term": "Rust概念241",
    "definition": "Rust概念241说明",
    "category": "Rust",
    "tags": [
      "Rust"
    ],
    "updatedAt": "2026-07-03T00:00:00.000Z"
  },
  {
    "id": "rs-glossary-243",
    "term": "Rust概念242",
    "definition": "Rust概念242说明",
    "category": "Rust",
    "tags": [
      "Rust"
    ],
    "updatedAt": "2026-07-03T00:00:00.000Z"
  },
  {
    "id": "rs-glossary-244",
    "term": "Rust概念243",
    "definition": "Rust概念243说明",
    "category": "Rust",
    "tags": [
      "Rust"
    ],
    "updatedAt": "2026-07-03T00:00:00.000Z"
  },
  {
    "id": "rs-glossary-245",
    "term": "Rust概念244",
    "definition": "Rust概念244说明",
    "category": "Rust",
    "tags": [
      "Rust"
    ],
    "updatedAt": "2026-07-03T00:00:00.000Z"
  },
  {
    "id": "rs-glossary-246",
    "term": "Rust概念245",
    "definition": "Rust概念245说明",
    "category": "Rust",
    "tags": [
      "Rust"
    ],
    "updatedAt": "2026-07-03T00:00:00.000Z"
  },
  {
    "id": "rs-glossary-247",
    "term": "Rust概念246",
    "definition": "Rust概念246说明",
    "category": "Rust",
    "tags": [
      "Rust"
    ],
    "updatedAt": "2026-07-03T00:00:00.000Z"
  },
  {
    "id": "rs-glossary-248",
    "term": "Rust概念247",
    "definition": "Rust概念247说明",
    "category": "Rust",
    "tags": [
      "Rust"
    ],
    "updatedAt": "2026-07-03T00:00:00.000Z"
  },
  {
    "id": "rs-glossary-249",
    "term": "Rust概念248",
    "definition": "Rust概念248说明",
    "category": "Rust",
    "tags": [
      "Rust"
    ],
    "updatedAt": "2026-07-03T00:00:00.000Z"
  },
  {
    "id": "rs-glossary-250",
    "term": "Rust概念249",
    "definition": "Rust概念249说明",
    "category": "Rust",
    "tags": [
      "Rust"
    ],
    "updatedAt": "2026-07-03T00:00:00.000Z"
  },
  {
    "id": "rs-glossary-251",
    "term": "Rust概念250",
    "definition": "Rust概念250说明",
    "category": "Rust",
    "tags": [
      "Rust"
    ],
    "updatedAt": "2026-07-03T00:00:00.000Z"
  },
  {
    "id": "rs-glossary-252",
    "term": "Rust概念251",
    "definition": "Rust概念251说明",
    "category": "Rust",
    "tags": [
      "Rust"
    ],
    "updatedAt": "2026-07-03T00:00:00.000Z"
  },
  {
    "id": "rs-glossary-253",
    "term": "Rust概念252",
    "definition": "Rust概念252说明",
    "category": "Rust",
    "tags": [
      "Rust"
    ],
    "updatedAt": "2026-07-03T00:00:00.000Z"
  },
  {
    "id": "rs-glossary-254",
    "term": "Rust概念253",
    "definition": "Rust概念253说明",
    "category": "Rust",
    "tags": [
      "Rust"
    ],
    "updatedAt": "2026-07-03T00:00:00.000Z"
  },
  {
    "id": "rs-glossary-255",
    "term": "Rust概念254",
    "definition": "Rust概念254说明",
    "category": "Rust",
    "tags": [
      "Rust"
    ],
    "updatedAt": "2026-07-03T00:00:00.000Z"
  },
  {
    "id": "rs-glossary-256",
    "term": "Rust概念255",
    "definition": "Rust概念255说明",
    "category": "Rust",
    "tags": [
      "Rust"
    ],
    "updatedAt": "2026-07-03T00:00:00.000Z"
  },
  {
    "id": "rs-glossary-257",
    "term": "Rust概念256",
    "definition": "Rust概念256说明",
    "category": "Rust",
    "tags": [
      "Rust"
    ],
    "updatedAt": "2026-07-03T00:00:00.000Z"
  },
  {
    "id": "rs-glossary-258",
    "term": "Rust概念257",
    "definition": "Rust概念257说明",
    "category": "Rust",
    "tags": [
      "Rust"
    ],
    "updatedAt": "2026-07-03T00:00:00.000Z"
  },
  {
    "id": "rs-glossary-259",
    "term": "Rust概念258",
    "definition": "Rust概念258说明",
    "category": "Rust",
    "tags": [
      "Rust"
    ],
    "updatedAt": "2026-07-03T00:00:00.000Z"
  },
  {
    "id": "rs-glossary-260",
    "term": "Rust概念259",
    "definition": "Rust概念259说明",
    "category": "Rust",
    "tags": [
      "Rust"
    ],
    "updatedAt": "2026-07-03T00:00:00.000Z"
  },
  {
    "id": "rs-glossary-261",
    "term": "Rust概念260",
    "definition": "Rust概念260说明",
    "category": "Rust",
    "tags": [
      "Rust"
    ],
    "updatedAt": "2026-07-03T00:00:00.000Z"
  },
  {
    "id": "rs-glossary-262",
    "term": "Rust概念261",
    "definition": "Rust概念261说明",
    "category": "Rust",
    "tags": [
      "Rust"
    ],
    "updatedAt": "2026-07-03T00:00:00.000Z"
  },
  {
    "id": "rs-glossary-263",
    "term": "Rust概念262",
    "definition": "Rust概念262说明",
    "category": "Rust",
    "tags": [
      "Rust"
    ],
    "updatedAt": "2026-07-03T00:00:00.000Z"
  },
  {
    "id": "rs-glossary-264",
    "term": "Rust概念263",
    "definition": "Rust概念263说明",
    "category": "Rust",
    "tags": [
      "Rust"
    ],
    "updatedAt": "2026-07-03T00:00:00.000Z"
  },
  {
    "id": "rs-glossary-265",
    "term": "Rust概念264",
    "definition": "Rust概念264说明",
    "category": "Rust",
    "tags": [
      "Rust"
    ],
    "updatedAt": "2026-07-03T00:00:00.000Z"
  },
  {
    "id": "rs-glossary-266",
    "term": "Rust概念265",
    "definition": "Rust概念265说明",
    "category": "Rust",
    "tags": [
      "Rust"
    ],
    "updatedAt": "2026-07-03T00:00:00.000Z"
  },
  {
    "id": "rs-glossary-267",
    "term": "Rust概念266",
    "definition": "Rust概念266说明",
    "category": "Rust",
    "tags": [
      "Rust"
    ],
    "updatedAt": "2026-07-03T00:00:00.000Z"
  },
  {
    "id": "rs-glossary-268",
    "term": "Rust概念267",
    "definition": "Rust概念267说明",
    "category": "Rust",
    "tags": [
      "Rust"
    ],
    "updatedAt": "2026-07-03T00:00:00.000Z"
  },
  {
    "id": "rs-glossary-269",
    "term": "Rust概念268",
    "definition": "Rust概念268说明",
    "category": "Rust",
    "tags": [
      "Rust"
    ],
    "updatedAt": "2026-07-03T00:00:00.000Z"
  },
  {
    "id": "rs-glossary-270",
    "term": "Rust概念269",
    "definition": "Rust概念269说明",
    "category": "Rust",
    "tags": [
      "Rust"
    ],
    "updatedAt": "2026-07-03T00:00:00.000Z"
  },
  {
    "id": "rs-glossary-271",
    "term": "Rust概念270",
    "definition": "Rust概念270说明",
    "category": "Rust",
    "tags": [
      "Rust"
    ],
    "updatedAt": "2026-07-03T00:00:00.000Z"
  },
  {
    "id": "rs-glossary-272",
    "term": "Rust概念271",
    "definition": "Rust概念271说明",
    "category": "Rust",
    "tags": [
      "Rust"
    ],
    "updatedAt": "2026-07-03T00:00:00.000Z"
  },
  {
    "id": "rs-glossary-273",
    "term": "Rust概念272",
    "definition": "Rust概念272说明",
    "category": "Rust",
    "tags": [
      "Rust"
    ],
    "updatedAt": "2026-07-03T00:00:00.000Z"
  },
  {
    "id": "rs-glossary-274",
    "term": "Rust概念273",
    "definition": "Rust概念273说明",
    "category": "Rust",
    "tags": [
      "Rust"
    ],
    "updatedAt": "2026-07-03T00:00:00.000Z"
  },
  {
    "id": "rs-glossary-275",
    "term": "Rust概念274",
    "definition": "Rust概念274说明",
    "category": "Rust",
    "tags": [
      "Rust"
    ],
    "updatedAt": "2026-07-03T00:00:00.000Z"
  },
  {
    "id": "rs-glossary-276",
    "term": "Rust概念275",
    "definition": "Rust概念275说明",
    "category": "Rust",
    "tags": [
      "Rust"
    ],
    "updatedAt": "2026-07-03T00:00:00.000Z"
  },
  {
    "id": "rs-glossary-277",
    "term": "Rust概念276",
    "definition": "Rust概念276说明",
    "category": "Rust",
    "tags": [
      "Rust"
    ],
    "updatedAt": "2026-07-03T00:00:00.000Z"
  },
  {
    "id": "rs-glossary-278",
    "term": "Rust概念277",
    "definition": "Rust概念277说明",
    "category": "Rust",
    "tags": [
      "Rust"
    ],
    "updatedAt": "2026-07-03T00:00:00.000Z"
  },
  {
    "id": "rs-glossary-279",
    "term": "Rust概念278",
    "definition": "Rust概念278说明",
    "category": "Rust",
    "tags": [
      "Rust"
    ],
    "updatedAt": "2026-07-03T00:00:00.000Z"
  },
  {
    "id": "rs-glossary-280",
    "term": "Rust概念279",
    "definition": "Rust概念279说明",
    "category": "Rust",
    "tags": [
      "Rust"
    ],
    "updatedAt": "2026-07-03T00:00:00.000Z"
  },
  {
    "id": "rs-glossary-281",
    "term": "Rust概念280",
    "definition": "Rust概念280说明",
    "category": "Rust",
    "tags": [
      "Rust"
    ],
    "updatedAt": "2026-07-03T00:00:00.000Z"
  },
  {
    "id": "rs-glossary-282",
    "term": "Rust概念281",
    "definition": "Rust概念281说明",
    "category": "Rust",
    "tags": [
      "Rust"
    ],
    "updatedAt": "2026-07-03T00:00:00.000Z"
  },
  {
    "id": "rs-glossary-283",
    "term": "Rust概念282",
    "definition": "Rust概念282说明",
    "category": "Rust",
    "tags": [
      "Rust"
    ],
    "updatedAt": "2026-07-03T00:00:00.000Z"
  },
  {
    "id": "rs-glossary-284",
    "term": "Rust概念283",
    "definition": "Rust概念283说明",
    "category": "Rust",
    "tags": [
      "Rust"
    ],
    "updatedAt": "2026-07-03T00:00:00.000Z"
  },
  {
    "id": "rs-glossary-285",
    "term": "Rust概念284",
    "definition": "Rust概念284说明",
    "category": "Rust",
    "tags": [
      "Rust"
    ],
    "updatedAt": "2026-07-03T00:00:00.000Z"
  },
  {
    "id": "rs-glossary-286",
    "term": "Rust概念285",
    "definition": "Rust概念285说明",
    "category": "Rust",
    "tags": [
      "Rust"
    ],
    "updatedAt": "2026-07-03T00:00:00.000Z"
  },
  {
    "id": "rs-glossary-287",
    "term": "Rust概念286",
    "definition": "Rust概念286说明",
    "category": "Rust",
    "tags": [
      "Rust"
    ],
    "updatedAt": "2026-07-03T00:00:00.000Z"
  },
  {
    "id": "rs-glossary-288",
    "term": "Rust概念287",
    "definition": "Rust概念287说明",
    "category": "Rust",
    "tags": [
      "Rust"
    ],
    "updatedAt": "2026-07-03T00:00:00.000Z"
  },
  {
    "id": "rs-glossary-289",
    "term": "Rust概念288",
    "definition": "Rust概念288说明",
    "category": "Rust",
    "tags": [
      "Rust"
    ],
    "updatedAt": "2026-07-03T00:00:00.000Z"
  },
  {
    "id": "rs-glossary-290",
    "term": "Rust概念289",
    "definition": "Rust概念289说明",
    "category": "Rust",
    "tags": [
      "Rust"
    ],
    "updatedAt": "2026-07-03T00:00:00.000Z"
  },
  {
    "id": "rs-glossary-291",
    "term": "Rust概念290",
    "definition": "Rust概念290说明",
    "category": "Rust",
    "tags": [
      "Rust"
    ],
    "updatedAt": "2026-07-03T00:00:00.000Z"
  },
  {
    "id": "rs-glossary-292",
    "term": "Rust概念291",
    "definition": "Rust概念291说明",
    "category": "Rust",
    "tags": [
      "Rust"
    ],
    "updatedAt": "2026-07-03T00:00:00.000Z"
  },
  {
    "id": "rs-glossary-293",
    "term": "Rust概念292",
    "definition": "Rust概念292说明",
    "category": "Rust",
    "tags": [
      "Rust"
    ],
    "updatedAt": "2026-07-03T00:00:00.000Z"
  },
  {
    "id": "rs-glossary-294",
    "term": "Rust概念293",
    "definition": "Rust概念293说明",
    "category": "Rust",
    "tags": [
      "Rust"
    ],
    "updatedAt": "2026-07-03T00:00:00.000Z"
  },
  {
    "id": "rs-glossary-295",
    "term": "Rust概念294",
    "definition": "Rust概念294说明",
    "category": "Rust",
    "tags": [
      "Rust"
    ],
    "updatedAt": "2026-07-03T00:00:00.000Z"
  },
  {
    "id": "rs-glossary-296",
    "term": "Rust概念295",
    "definition": "Rust概念295说明",
    "category": "Rust",
    "tags": [
      "Rust"
    ],
    "updatedAt": "2026-07-03T00:00:00.000Z"
  },
  {
    "id": "rs-glossary-297",
    "term": "Rust概念296",
    "definition": "Rust概念296说明",
    "category": "Rust",
    "tags": [
      "Rust"
    ],
    "updatedAt": "2026-07-03T00:00:00.000Z"
  },
  {
    "id": "rs-glossary-298",
    "term": "Rust概念297",
    "definition": "Rust概念297说明",
    "category": "Rust",
    "tags": [
      "Rust"
    ],
    "updatedAt": "2026-07-03T00:00:00.000Z"
  },
  {
    "id": "rs-glossary-299",
    "term": "Rust概念298",
    "definition": "Rust概念298说明",
    "category": "Rust",
    "tags": [
      "Rust"
    ],
    "updatedAt": "2026-07-03T00:00:00.000Z"
  },
  {
    "id": "rs-glossary-300",
    "term": "Rust概念299",
    "definition": "Rust概念299说明",
    "category": "Rust",
    "tags": [
      "Rust"
    ],
    "updatedAt": "2026-07-03T00:00:00.000Z"
  },
  {
    "id": "rs-glossary-301",
    "term": "Rust概念300",
    "definition": "Rust概念300说明",
    "category": "Rust",
    "tags": [
      "Rust"
    ],
    "updatedAt": "2026-07-03T00:00:00.000Z"
  },
  {
    "id": "rs-glossary-302",
    "term": "Rust概念301",
    "definition": "Rust概念301说明",
    "category": "Rust",
    "tags": [
      "Rust"
    ],
    "updatedAt": "2026-07-03T00:00:00.000Z"
  },
  {
    "id": "rs-glossary-303",
    "term": "Rust概念302",
    "definition": "Rust概念302说明",
    "category": "Rust",
    "tags": [
      "Rust"
    ],
    "updatedAt": "2026-07-03T00:00:00.000Z"
  },
  {
    "id": "rs-glossary-304",
    "term": "Rust概念303",
    "definition": "Rust概念303说明",
    "category": "Rust",
    "tags": [
      "Rust"
    ],
    "updatedAt": "2026-07-03T00:00:00.000Z"
  },
  {
    "id": "rs-glossary-305",
    "term": "Rust概念304",
    "definition": "Rust概念304说明",
    "category": "Rust",
    "tags": [
      "Rust"
    ],
    "updatedAt": "2026-07-03T00:00:00.000Z"
  },
  {
    "id": "rs-glossary-306",
    "term": "Rust概念305",
    "definition": "Rust概念305说明",
    "category": "Rust",
    "tags": [
      "Rust"
    ],
    "updatedAt": "2026-07-03T00:00:00.000Z"
  },
  {
    "id": "rs-glossary-307",
    "term": "Rust概念306",
    "definition": "Rust概念306说明",
    "category": "Rust",
    "tags": [
      "Rust"
    ],
    "updatedAt": "2026-07-03T00:00:00.000Z"
  },
  {
    "id": "rs-glossary-308",
    "term": "Rust概念307",
    "definition": "Rust概念307说明",
    "category": "Rust",
    "tags": [
      "Rust"
    ],
    "updatedAt": "2026-07-03T00:00:00.000Z"
  },
  {
    "id": "rs-glossary-309",
    "term": "Rust概念308",
    "definition": "Rust概念308说明",
    "category": "Rust",
    "tags": [
      "Rust"
    ],
    "updatedAt": "2026-07-03T00:00:00.000Z"
  },
  {
    "id": "rs-glossary-310",
    "term": "Rust概念309",
    "definition": "Rust概念309说明",
    "category": "Rust",
    "tags": [
      "Rust"
    ],
    "updatedAt": "2026-07-03T00:00:00.000Z"
  },
  {
    "id": "rs-glossary-311",
    "term": "Rust概念310",
    "definition": "Rust概念310说明",
    "category": "Rust",
    "tags": [
      "Rust"
    ],
    "updatedAt": "2026-07-03T00:00:00.000Z"
  },
  {
    "id": "rs-glossary-312",
    "term": "Rust概念311",
    "definition": "Rust概念311说明",
    "category": "Rust",
    "tags": [
      "Rust"
    ],
    "updatedAt": "2026-07-03T00:00:00.000Z"
  },
  {
    "id": "rs-glossary-313",
    "term": "Rust概念312",
    "definition": "Rust概念312说明",
    "category": "Rust",
    "tags": [
      "Rust"
    ],
    "updatedAt": "2026-07-03T00:00:00.000Z"
  },
  {
    "id": "rs-glossary-314",
    "term": "Rust概念313",
    "definition": "Rust概念313说明",
    "category": "Rust",
    "tags": [
      "Rust"
    ],
    "updatedAt": "2026-07-03T00:00:00.000Z"
  },
  {
    "id": "rs-glossary-315",
    "term": "Rust概念314",
    "definition": "Rust概念314说明",
    "category": "Rust",
    "tags": [
      "Rust"
    ],
    "updatedAt": "2026-07-03T00:00:00.000Z"
  },
  {
    "id": "rs-glossary-316",
    "term": "Rust概念315",
    "definition": "Rust概念315说明",
    "category": "Rust",
    "tags": [
      "Rust"
    ],
    "updatedAt": "2026-07-03T00:00:00.000Z"
  },
  {
    "id": "rs-glossary-317",
    "term": "Rust概念316",
    "definition": "Rust概念316说明",
    "category": "Rust",
    "tags": [
      "Rust"
    ],
    "updatedAt": "2026-07-03T00:00:00.000Z"
  },
  {
    "id": "rs-glossary-318",
    "term": "Rust概念317",
    "definition": "Rust概念317说明",
    "category": "Rust",
    "tags": [
      "Rust"
    ],
    "updatedAt": "2026-07-03T00:00:00.000Z"
  },
  {
    "id": "rs-glossary-319",
    "term": "Rust概念318",
    "definition": "Rust概念318说明",
    "category": "Rust",
    "tags": [
      "Rust"
    ],
    "updatedAt": "2026-07-03T00:00:00.000Z"
  },
  {
    "id": "rs-glossary-320",
    "term": "Rust概念319",
    "definition": "Rust概念319说明",
    "category": "Rust",
    "tags": [
      "Rust"
    ],
    "updatedAt": "2026-07-03T00:00:00.000Z"
  },
  {
    "id": "rs-glossary-321",
    "term": "Rust概念320",
    "definition": "Rust概念320说明",
    "category": "Rust",
    "tags": [
      "Rust"
    ],
    "updatedAt": "2026-07-03T00:00:00.000Z"
  },
  {
    "id": "rs-glossary-322",
    "term": "Rust概念321",
    "definition": "Rust概念321说明",
    "category": "Rust",
    "tags": [
      "Rust"
    ],
    "updatedAt": "2026-07-03T00:00:00.000Z"
  },
  {
    "id": "rs-glossary-323",
    "term": "Rust概念322",
    "definition": "Rust概念322说明",
    "category": "Rust",
    "tags": [
      "Rust"
    ],
    "updatedAt": "2026-07-03T00:00:00.000Z"
  },
  {
    "id": "rs-glossary-324",
    "term": "Rust概念323",
    "definition": "Rust概念323说明",
    "category": "Rust",
    "tags": [
      "Rust"
    ],
    "updatedAt": "2026-07-03T00:00:00.000Z"
  },
  {
    "id": "rs-glossary-325",
    "term": "Rust概念324",
    "definition": "Rust概念324说明",
    "category": "Rust",
    "tags": [
      "Rust"
    ],
    "updatedAt": "2026-07-03T00:00:00.000Z"
  },
  {
    "id": "rs-glossary-326",
    "term": "Rust概念325",
    "definition": "Rust概念325说明",
    "category": "Rust",
    "tags": [
      "Rust"
    ],
    "updatedAt": "2026-07-03T00:00:00.000Z"
  },
  {
    "id": "rs-glossary-327",
    "term": "Rust概念326",
    "definition": "Rust概念326说明",
    "category": "Rust",
    "tags": [
      "Rust"
    ],
    "updatedAt": "2026-07-03T00:00:00.000Z"
  },
  {
    "id": "rs-glossary-328",
    "term": "Rust概念327",
    "definition": "Rust概念327说明",
    "category": "Rust",
    "tags": [
      "Rust"
    ],
    "updatedAt": "2026-07-03T00:00:00.000Z"
  },
  {
    "id": "rs-glossary-329",
    "term": "Rust概念328",
    "definition": "Rust概念328说明",
    "category": "Rust",
    "tags": [
      "Rust"
    ],
    "updatedAt": "2026-07-03T00:00:00.000Z"
  },
  {
    "id": "rs-glossary-330",
    "term": "Rust概念329",
    "definition": "Rust概念329说明",
    "category": "Rust",
    "tags": [
      "Rust"
    ],
    "updatedAt": "2026-07-03T00:00:00.000Z"
  },
  {
    "id": "rs-glossary-331",
    "term": "Rust概念330",
    "definition": "Rust概念330说明",
    "category": "Rust",
    "tags": [
      "Rust"
    ],
    "updatedAt": "2026-07-03T00:00:00.000Z"
  },
  {
    "id": "rs-glossary-332",
    "term": "Rust概念331",
    "definition": "Rust概念331说明",
    "category": "Rust",
    "tags": [
      "Rust"
    ],
    "updatedAt": "2026-07-03T00:00:00.000Z"
  },
  {
    "id": "rs-glossary-333",
    "term": "Rust概念332",
    "definition": "Rust概念332说明",
    "category": "Rust",
    "tags": [
      "Rust"
    ],
    "updatedAt": "2026-07-03T00:00:00.000Z"
  },
  {
    "id": "rs-glossary-334",
    "term": "Rust概念333",
    "definition": "Rust概念333说明",
    "category": "Rust",
    "tags": [
      "Rust"
    ],
    "updatedAt": "2026-07-03T00:00:00.000Z"
  },
  {
    "id": "rs-glossary-335",
    "term": "Rust概念334",
    "definition": "Rust概念334说明",
    "category": "Rust",
    "tags": [
      "Rust"
    ],
    "updatedAt": "2026-07-03T00:00:00.000Z"
  },
  {
    "id": "rs-glossary-336",
    "term": "Rust概念335",
    "definition": "Rust概念335说明",
    "category": "Rust",
    "tags": [
      "Rust"
    ],
    "updatedAt": "2026-07-03T00:00:00.000Z"
  },
  {
    "id": "rs-glossary-337",
    "term": "Rust概念336",
    "definition": "Rust概念336说明",
    "category": "Rust",
    "tags": [
      "Rust"
    ],
    "updatedAt": "2026-07-03T00:00:00.000Z"
  },
  {
    "id": "rs-glossary-338",
    "term": "Rust概念337",
    "definition": "Rust概念337说明",
    "category": "Rust",
    "tags": [
      "Rust"
    ],
    "updatedAt": "2026-07-03T00:00:00.000Z"
  },
  {
    "id": "rs-glossary-339",
    "term": "Rust概念338",
    "definition": "Rust概念338说明",
    "category": "Rust",
    "tags": [
      "Rust"
    ],
    "updatedAt": "2026-07-03T00:00:00.000Z"
  },
  {
    "id": "rs-glossary-340",
    "term": "Rust概念339",
    "definition": "Rust概念339说明",
    "category": "Rust",
    "tags": [
      "Rust"
    ],
    "updatedAt": "2026-07-03T00:00:00.000Z"
  },
  {
    "id": "rs-glossary-341",
    "term": "Rust概念340",
    "definition": "Rust概念340说明",
    "category": "Rust",
    "tags": [
      "Rust"
    ],
    "updatedAt": "2026-07-03T00:00:00.000Z"
  },
  {
    "id": "rs-glossary-342",
    "term": "Rust概念341",
    "definition": "Rust概念341说明",
    "category": "Rust",
    "tags": [
      "Rust"
    ],
    "updatedAt": "2026-07-03T00:00:00.000Z"
  },
  {
    "id": "rs-glossary-343",
    "term": "Rust概念342",
    "definition": "Rust概念342说明",
    "category": "Rust",
    "tags": [
      "Rust"
    ],
    "updatedAt": "2026-07-03T00:00:00.000Z"
  },
  {
    "id": "rs-glossary-344",
    "term": "Rust概念343",
    "definition": "Rust概念343说明",
    "category": "Rust",
    "tags": [
      "Rust"
    ],
    "updatedAt": "2026-07-03T00:00:00.000Z"
  },
  {
    "id": "rs-glossary-345",
    "term": "Rust概念344",
    "definition": "Rust概念344说明",
    "category": "Rust",
    "tags": [
      "Rust"
    ],
    "updatedAt": "2026-07-03T00:00:00.000Z"
  },
  {
    "id": "rs-glossary-346",
    "term": "Rust概念345",
    "definition": "Rust概念345说明",
    "category": "Rust",
    "tags": [
      "Rust"
    ],
    "updatedAt": "2026-07-03T00:00:00.000Z"
  },
  {
    "id": "rs-glossary-347",
    "term": "Rust概念346",
    "definition": "Rust概念346说明",
    "category": "Rust",
    "tags": [
      "Rust"
    ],
    "updatedAt": "2026-07-03T00:00:00.000Z"
  },
  {
    "id": "rs-glossary-348",
    "term": "Rust概念347",
    "definition": "Rust概念347说明",
    "category": "Rust",
    "tags": [
      "Rust"
    ],
    "updatedAt": "2026-07-03T00:00:00.000Z"
  },
  {
    "id": "rs-glossary-349",
    "term": "Rust概念348",
    "definition": "Rust概念348说明",
    "category": "Rust",
    "tags": [
      "Rust"
    ],
    "updatedAt": "2026-07-03T00:00:00.000Z"
  },
  {
    "id": "rs-glossary-350",
    "term": "Rust概念349",
    "definition": "Rust概念349说明",
    "category": "Rust",
    "tags": [
      "Rust"
    ],
    "updatedAt": "2026-07-03T00:00:00.000Z"
  },
  {
    "id": "rs-glossary-351",
    "term": "Rust概念350",
    "definition": "Rust概念350说明",
    "category": "Rust",
    "tags": [
      "Rust"
    ],
    "updatedAt": "2026-07-03T00:00:00.000Z"
  },
  {
    "id": "rs-glossary-352",
    "term": "Rust概念351",
    "definition": "Rust概念351说明",
    "category": "Rust",
    "tags": [
      "Rust"
    ],
    "updatedAt": "2026-07-03T00:00:00.000Z"
  },
  {
    "id": "rs-glossary-353",
    "term": "Rust概念352",
    "definition": "Rust概念352说明",
    "category": "Rust",
    "tags": [
      "Rust"
    ],
    "updatedAt": "2026-07-03T00:00:00.000Z"
  },
  {
    "id": "rs-glossary-354",
    "term": "Rust概念353",
    "definition": "Rust概念353说明",
    "category": "Rust",
    "tags": [
      "Rust"
    ],
    "updatedAt": "2026-07-03T00:00:00.000Z"
  },
  {
    "id": "rs-glossary-355",
    "term": "Rust概念354",
    "definition": "Rust概念354说明",
    "category": "Rust",
    "tags": [
      "Rust"
    ],
    "updatedAt": "2026-07-03T00:00:00.000Z"
  },
  {
    "id": "rs-glossary-356",
    "term": "Rust概念355",
    "definition": "Rust概念355说明",
    "category": "Rust",
    "tags": [
      "Rust"
    ],
    "updatedAt": "2026-07-03T00:00:00.000Z"
  },
  {
    "id": "rs-glossary-357",
    "term": "Rust概念356",
    "definition": "Rust概念356说明",
    "category": "Rust",
    "tags": [
      "Rust"
    ],
    "updatedAt": "2026-07-03T00:00:00.000Z"
  },
  {
    "id": "rs-glossary-358",
    "term": "Rust概念357",
    "definition": "Rust概念357说明",
    "category": "Rust",
    "tags": [
      "Rust"
    ],
    "updatedAt": "2026-07-03T00:00:00.000Z"
  },
  {
    "id": "rs-glossary-359",
    "term": "Rust概念358",
    "definition": "Rust概念358说明",
    "category": "Rust",
    "tags": [
      "Rust"
    ],
    "updatedAt": "2026-07-03T00:00:00.000Z"
  },
  {
    "id": "rs-glossary-360",
    "term": "Rust概念359",
    "definition": "Rust概念359说明",
    "category": "Rust",
    "tags": [
      "Rust"
    ],
    "updatedAt": "2026-07-03T00:00:00.000Z"
  }
]